README.rst
setup.py
PySPED.egg-info/PKG-INFO
PySPED.egg-info/SOURCES.txt
PySPED.egg-info/dependency_links.txt
PySPED.egg-info/top_level.txt
pysped/__init__.py
pysped/cte/__init__.py
pysped/cte/webservices.py
pysped/cte/webservices_flags.py
pysped/cte/dacte/__init__.py
pysped/cte/leiaute/__init__.py
pysped/cte/leiaute/canccte_104.py
pysped/cte/leiaute/canccte_300.py
pysped/cte/leiaute/consrecicte_104.py
pysped/cte/leiaute/consrecicte_300.py
pysped/cte/leiaute/conssitcte_104.py
pysped/cte/leiaute/conssitcte_300.py
pysped/cte/leiaute/consstatserv_104.py
pysped/cte/leiaute/consstatserv_300.py
pysped/cte/leiaute/cte_104.py
pysped/cte/leiaute/cte_300.py
pysped/cte/leiaute/envicte_104.py
pysped/cte/leiaute/envicte_300.py
pysped/cte/leiaute/eventoscte_300.py
pysped/cte/leiaute/inutcte_104.py
pysped/cte/leiaute/inutcte_300.py
pysped/cte/leiaute/modais_300.py
pysped/cte/leiaute/proceventocte_300.py
pysped/cte/leiaute/soap_104.py
pysped/cte/leiaute/soap_300.py
pysped/cte/leiaute/schema/PL_CTe_300/consReciCTeTiposBasico_v3.00.xsd
pysped/cte/leiaute/schema/PL_CTe_300/consReciCTe_v3.00.xsd
pysped/cte/leiaute/schema/PL_CTe_300/consSitCTeTiposBasico_v3.00.xsd
pysped/cte/leiaute/schema/PL_CTe_300/consSitCTe_v3.00.xsd
pysped/cte/leiaute/schema/PL_CTe_300/consStatServCTe_v3.00.xsd
pysped/cte/leiaute/schema/PL_CTe_300/consStatServTiposBasico_v3.00.xsd
pysped/cte/leiaute/schema/PL_CTe_300/cteModalAereo_v3.00.xsd
pysped/cte/leiaute/schema/PL_CTe_300/cteModalAquaviario_v3.00.xsd
pysped/cte/leiaute/schema/PL_CTe_300/cteModalDutoviario_v3.00.xsd
pysped/cte/leiaute/schema/PL_CTe_300/cteModalFerroviario_v3.00.xsd
pysped/cte/leiaute/schema/PL_CTe_300/cteModalRodoviarioOS_v3.00.xsd
pysped/cte/leiaute/schema/PL_CTe_300/cteModalRodoviario_v3.00.xsd
pysped/cte/leiaute/schema/PL_CTe_300/cteMultiModal_v3.00.xsd
pysped/cte/leiaute/schema/PL_CTe_300/cteOS_v3.00.xsd
pysped/cte/leiaute/schema/PL_CTe_300/cteTiposBasico_v3.00.xsd
pysped/cte/leiaute/schema/PL_CTe_300/cte_v3.00.xsd
pysped/cte/leiaute/schema/PL_CTe_300/enviCTe_v3.00.xsd
pysped/cte/leiaute/schema/PL_CTe_300/evCCeCTe_v3.00.xsd
